{
  "totalEpisodes": 4181,
  "podcastCounts": {
    "Lex Fridman": 200,
    "The Joe Rogan": 200,
    "Huberman Lab": 200,
    "WTF is with Nikhil Kamath": 39,
    "Waveform: The MKBHD Podcast": 400,
    "TED Talks Daily": 200,
    "99% Invisible": 200,
    "UX coffee break with UX Anudeep": 69,
    "Intercom on Product": 39,
    "Dateline NBC": 200,
    "WVFRM": 0,
    "SmartLess": 200,
    "This American Life": 11,
    "Morbid": 200,
    "Crime Junkie": 200,
    "Up First": 200,
    "Hidden Brain": 200,
    "Puri Jagannadh": 200,
    "Stuff you should know": 200,
    "Call Her Daddy": 200,
    "Anything Goes with Emma Chamberlain": 200,
    "On Purpose with Jay Shetty": 150,
    "The Diary Of A CEO with Steven Bartlett": 200,
    "Wiser Than Me with Julia Louis-Dreyfus": 42,
    "New Heights with Jason & Travis Kelce": 139,
    "Heavyweight": 92
  },
  "fetchDate": "2025-05-01T21:05:02.086Z"
}